<?xml version="1.0" encoding="UTF-8"?>
<objects serializationModel="Studio.02.02.00">
	<object class="AudioFile" id="{d673100b-d411-4d94-82a7-69a21f398fda}">
		<property name="assetPath">
			<value>Walk_Snow_1.wav</value>
		</property>
		<property name="frequencyInKHz">
			<value>44.0999985</value>
		</property>
		<property name="channelCount">
			<value>1</value>
		</property>
		<property name="length">
			<value>0.86349206349206353</value>
		</property>
		<relationship name="masterAssetFolder">
			<destination>{e042d01d-2152-41ad-b48c-6214f6bf4d60}</destination>
		</relationship>
	</object>
</objects>
